charta/__init__.py
charta/charts.py
charta/client.py
charta/common.py
charta/server.py
charta/static/dashboard.js
charta/static/index.html
charta/static/interactions.js
charta/static/main.js
charta/static/style.css
charta/static/utils.js
charta-0.0a7.data/scripts/charta-server
charta-0.0a7.dist-info/LICENSE
charta-0.0a7.dist-info/METADATA
charta-0.0a7.dist-info/WHEEL
charta-0.0a7.dist-info/top_level.txt
charta-0.0a7.dist-info/RECORD
