Metadata-Version: 2.1
Name: charta
Version: 0.0a7
Summary: A package for building realtime dashboards. Originally designed for monitoring the progress of optimization problems.
Home-page: https://github.com/pvarin/charta
Author: Patrick Varin
Author-email: patrickjvarin@gmail.com
License: UNKNOWN
Platform: UNKNOWN
Classifier: Programming Language :: Python :: 3
Classifier: License :: OSI Approved :: BSD License
Classifier: Development Status :: 2 - Pre-Alpha
Classifier: Operating System :: OS Independent
Requires-Python: >=3.6
License-File: LICENSE
Requires-Dist: pyzmq
Requires-Dist: tornado
Requires-Dist: numpy
